CHANGES.txt
MANIFEST.in
README.rst
VERSION
requirements-dev.txt
requirements-test.txt
requirements.txt
setup.py
thumbor_rekognition/__init__.py
thumbor_rekognition.egg-info/PKG-INFO
thumbor_rekognition.egg-info/SOURCES.txt
thumbor_rekognition.egg-info/dependency_links.txt
thumbor_rekognition.egg-info/requires.txt
thumbor_rekognition.egg-info/top_level.txt