Metadata-Version: 1.0
Name: thumbor-rekognition
Version: 0.1.1
Summary: Enable thumbor to use AWS rekognition to run face detection
Home-page: https://github.com/yu-liang-kono/thumbor_rekognition
Author: Yu Liang
Author-email: yu.liang@thekono.com
License: MIT License
